requirements.in
sshmitmcore/__init__.py
sshmitmcore/authentication.py
sshmitmcore/cli.py
sshmitmcore/compat.py
sshmitmcore/exceptions.py
sshmitmcore/logger.py
sshmitmcore/multisocket.py
sshmitmcore/project_metadata.py
sshmitmcore/server.py
sshmitmcore/session.py
sshmitmcore/sshkeys.py
sshmitmcore/clients/__init__.py
sshmitmcore/clients/sftp.py
sshmitmcore/clients/ssh.py
sshmitmcore/commands/__init__.py
sshmitmcore/commands/server.py
sshmitmcore/data/default.ini
sshmitmcore/forwarders/__init__.py
sshmitmcore/forwarders/agent.py
sshmitmcore/forwarders/base.py
sshmitmcore/forwarders/scp.py
sshmitmcore/forwarders/sftp.py
sshmitmcore/forwarders/ssh.py
sshmitmcore/forwarders/tunnel.py
sshmitmcore/interfaces/__init__.py
sshmitmcore/interfaces/server.py
sshmitmcore/interfaces/sftp.py
sshmitmcore/moduleparser/__init__.py
sshmitmcore/moduleparser/baseparser.py
sshmitmcore/moduleparser/exceptions.py
sshmitmcore/moduleparser/formatter.py
sshmitmcore/moduleparser/modules.py
sshmitmcore/moduleparser/parser.py
sshmitmcore/moduleparser/utils.py
sshmitmcore/workarounds/__init__.py
sshmitmcore/workarounds/monkeypatch.py
sshmitmcore/workarounds/transport.py
ssh_mitm_core-0.0.1.dist-info/METADATA
ssh_mitm_core-0.0.1.dist-info/WHEEL
ssh_mitm_core-0.0.1.dist-info/entry_points.txt
ssh_mitm_core-0.0.1.dist-info/licenses/LICENSE
ssh_mitm_core-0.0.1.dist-info/RECORD
